ape_solidity/__init__.py
ape_solidity/_cli.py
ape_solidity/_models.py
ape_solidity/_utils.py
ape_solidity/compiler.py
ape_solidity/exceptions.py
ape_solidity/py.typed
ape_solidity/version.py
ape_solidity-0.8.5.dist-info/LICENSE
ape_solidity-0.8.5.dist-info/METADATA
ape_solidity-0.8.5.dist-info/WHEEL
ape_solidity-0.8.5.dist-info/entry_points.txt
ape_solidity-0.8.5.dist-info/top_level.txt
ape_solidity-0.8.5.dist-info/RECORD
