Metadata-Version: 2.1
Name: ape-solidity
Version: 0.8.5
Summary: Plugin for Ape Ethereum Framework for compiling Solidity contracts
Home-page: https://github.com/ApeWorX/ape-solidity
Author: ApeWorX Ltd.
Author-email: admin@apeworx.io
License: Apache-2.0
Keywords: ethereum
Classifier: Development Status :: 5 - Production/Stable
Classifier: Intended Audience :: Developers
Classifier: License :: OSI Approved :: MIT License
Classifier: Natural Language :: English
Classifier: Operating System :: MacOS
Classifier: Operating System :: POSIX
Classifier: Programming Language :: Python :: 3
Classifier: Programming Language :: Python :: 3.9
Classifier: Programming Language :: Python :: 3.10
Classifier: Programming Language :: Python :: 3.11
Classifier: Programming Language :: Python :: 3.12
Requires-Python: >=3.9,<4
Provides-Extra: test
Provides-Extra: lint
Provides-Extra: doc
Provides-Extra: release
Provides-Extra: dev
License-File: LICENSE
